fmm3dpy/__init__.py
fmm3dpy/fmm3d.py
fmm3dpy/hfmm3d_fortran.cpython-311-darwin.so
fmm3dpy/stfmm3d_fortran.cpython-311-darwin.so
fmm3dpy/lfmm3d_fortran.cpython-311-darwin.so
fmm3dpy/emfmm3d_fortran.cpython-311-darwin.so
fmm3dpy-1.0.0.dist-info/RECORD
fmm3dpy-1.0.0.dist-info/WHEEL
fmm3dpy-1.0.0.dist-info/top_level.txt
fmm3dpy-1.0.0.dist-info/METADATA
